MANIFEST.in
setup.py
vn_core_nlp/__init__.py
vn_core_nlp.egg-info/PKG-INFO
vn_core_nlp.egg-info/SOURCES.txt
vn_core_nlp.egg-info/dependency_links.txt
vn_core_nlp.egg-info/not-zip-safe
vn_core_nlp.egg-info/requires.txt
vn_core_nlp.egg-info/top_level.txt
vn_core_nlp/preprocessing/__init__.py
vn_core_nlp/preprocessing/__init__.pyc
vn_core_nlp/preprocessing/pos_tagger/__init__.py
vn_core_nlp/preprocessing/pos_tagger/__init__.pyc
vn_core_nlp/preprocessing/pos_tagger/pos_tagger.py
vn_core_nlp/preprocessing/pos_tagger/pos_tagger.pyc
vn_core_nlp/preprocessing/pos_tagger/vn.hus.nlp.tagger-4.2.0-bin/CHANGES.txt
vn_core_nlp/preprocessing/pos_tagger/vn.hus.nlp.tagger-4.2.0-bin/LICENSE.txt
vn_core_nlp/preprocessing/pos_tagger/vn.hus.nlp.tagger-4.2.0-bin/README.txt
vn_core_nlp/preprocessing/pos_tagger/vn.hus.nlp.tagger-4.2.0-bin/tokenizer.log
vn_core_nlp/preprocessing/pos_tagger/vn.hus.nlp.tagger-4.2.0-bin/vn.hus.nlp.tagger-4.2.0.jar
vn_core_nlp/preprocessing/pos_tagger/vn.hus.nlp.tagger-4.2.0-bin/vnTagger.bat
vn_core_nlp/preprocessing/pos_tagger/vn.hus.nlp.tagger-4.2.0-bin/vnTagger.sh
vn_core_nlp/preprocessing/pos_tagger/vn.hus.nlp.tagger-4.2.0-bin/lib/commons-cli-1.2.jar
vn_core_nlp/preprocessing/pos_tagger/vn.hus.nlp.tagger-4.2.0-bin/lib/edu.stanford.nlp.tagger-2.0.jar
vn_core_nlp/preprocessing/pos_tagger/vn.hus.nlp.tagger-4.2.0-bin/lib/vn.hus.nlp.fsm-1.0.0.jar
vn_core_nlp/preprocessing/pos_tagger/vn.hus.nlp.tagger-4.2.0-bin/lib/vn.hus.nlp.tokenizer-4.1.1.jar
vn_core_nlp/preprocessing/pos_tagger/vn.hus.nlp.tagger-4.2.0-bin/lib/vn.hus.nlp.utils-1.0.0.jar
vn_core_nlp/preprocessing/pos_tagger/vn.hus.nlp.tagger-4.2.0-bin/resources/automata/dfaLexicon.xml
vn_core_nlp/preprocessing/pos_tagger/vn.hus.nlp.tagger-4.2.0-bin/resources/automata/externalLexicon.xml
vn_core_nlp/preprocessing/pos_tagger/vn.hus.nlp.tagger-4.2.0-bin/resources/bigram/bigram.xml
vn_core_nlp/preprocessing/pos_tagger/vn.hus.nlp.tagger-4.2.0-bin/resources/bigram/unigram.xml
vn_core_nlp/preprocessing/pos_tagger/vn.hus.nlp.tagger-4.2.0-bin/resources/lexers/lexers.xml
vn_core_nlp/preprocessing/pos_tagger/vn.hus.nlp.tagger-4.2.0-bin/resources/models/vtb.tagger
