Metadata-Version: 1.0
Name: vn-core-nlp
Version: 0.2.0
Summary: The python package for vietnamese text processing
Home-page: UNKNOWN
Author: Hoang Pham
Author-email: phamthaihoang.hn@gmail.com
License: UNKNOWN
Platform: UNKNOWN
